dox_trace/__init__.py
dox_trace/backward_refs.py
dox_trace/checks.py
dox_trace/config.py
dox_trace/coverage.py
dox_trace/dim_write.py
dox_trace/directives.py
dox_trace/enclosed.py
dox_trace/env.py
dox_trace/helper.py
dox_trace/main.py
dox_trace/properties.py
dox_trace/report.py
dox_trace/report_architecture.py
dox_trace/report_generic.py
dox_trace/report_input.py
dox_trace/report_module.py
dox_trace/report_source.py
dox_trace/report_table.py
dox_trace/roles.py
dox_trace/undefined_refs.py
dox_trace/version.py
dox_trace/yaml.py
dox_trace/_static/dox_trace.css
dox_trace/_static/dox_trace.js
dox_trace-3.0.0.dist-info/LICENSE
dox_trace-3.0.0.dist-info/METADATA
dox_trace-3.0.0.dist-info/WHEEL
dox_trace-3.0.0.dist-info/top_level.txt
dox_trace-3.0.0.dist-info/RECORD
